LICENSE
MANIFEST.in
README.md
setup.py
dexcom_reader/__init__.py
dexcom_reader/constants.py
dexcom_reader/crc16.py
dexcom_reader/database_records.py
dexcom_reader/packetwriter.py
dexcom_reader/readdata.py
dexcom_reader/record_test.py
dexcom_reader/util.py
dexcom_reader.egg-info/PKG-INFO
dexcom_reader.egg-info/SOURCES.txt
dexcom_reader.egg-info/dependency_links.txt
dexcom_reader.egg-info/not-zip-safe
dexcom_reader.egg-info/requires.txt
dexcom_reader.egg-info/top_level.txt
dexcom_reader/etc/udev/rules.d/80-dexcom.rules