Metadata-Version: 1.1
Name: dexcom_reader
Version: 0.1.9
Summary: Audit, and inspect data from Dexcom G4.
Home-page: https://github.com/openaps/dexcom_reader
Author: Ben West
Author-email: bewest+dexcom_reader@gmail.com
License: UNKNOWN
Platform: UNKNOWN
Classifier: Development Status :: 3 - Alpha
Classifier: Intended Audience :: Developers
Classifier: Intended Audience :: Science/Research
Classifier: Programming Language :: Python
Classifier: Topic :: Scientific/Engineering
Classifier: Topic :: Software Development :: Libraries
